[
  {
    "type": "BROKEN-IMG",
    "page": "homepage-desktop",
    "msg": "Imagem partida",
    "detail": "https://images.unsplash.com/photo-1584994434781-24fca0627b0d?crop=entropy&cs=tinysrgb&fit=max&fm=jpg&q=80&w=1080"
  },
  {
    "type": "BROKEN-IMG",
    "page": "homepage-desktop",
    "msg": "Imagem partida",
    "detail": "https://images.unsplash.com/photo-1635777253239-a30c19e79316?crop=entropy&cs=tinysrgb&fit=max&fm=jpg&q=80&w=1080"
  },
  {
    "type": "BROKEN-IMG",
    "page": "homepage-desktop",
    "msg": "Imagem partida",
    "detail": "https://images.unsplash.com/photo-1598534850992-5097de4a20fb?auto=format&fit=crop&w=1200&q=80"
  },
  {
    "type": "BROKEN-IMG",
    "page": "homepage-desktop",
    "msg": "Imagem partida",
    "detail": "https://images.unsplash.com/photo-1683549812226-f5904550ebf6?crop=entropy&cs=tinysrgb&fit=max&fm=jpg&q=80&w=1080"
  },
  {
    "type": "BROKEN-IMG",
    "page": "homepage-desktop",
    "msg": "Imagem partida",
    "detail": "https://images.unsplash.com/photo-1663602656480-c96f6f0a6f91?crop=entropy&cs=tinysrgb&fit=max&fm=jpg&q=80&w=1080"
  },
  {
    "type": "BROKEN-IMG",
    "page": "homepage-desktop",
    "msg": "Imagem partida",
    "detail": "https://images.unsplash.com/photo-1663313991553-6bb40f655023?crop=entropy&cs=tinysrgb&fit=max&fm=jpg&q=80&w=1080"
  },
  {
    "type": "CTA-NO-DEST",
    "page": "homepage-desktop",
    "msg": "CTA sem destino real: \"Ver Alojamento\"",
    "detail": ""
  },
  {
    "type": "CTA-NO-DEST",
    "page": "homepage-desktop",
    "msg": "CTA sem destino real: \"Ver Experiências\"",
    "detail": ""
  },
  {
    "type": "CTA-NO-DEST",
    "page": "homepage-desktop",
    "msg": "CTA sem destino real: \"Ver Equipamento\"",
    "detail": ""
  },
  {
    "type": "BROKEN-IMG",
    "page": "beaches-desktop",
    "msg": "Imagem partida",
    "detail": "https://images.unsplash.com/photo-1651237031934-4c1c78b9f1ba?auto=format&fit=crop&w=1200&q=80"
  },
  {
    "type": "BROKEN-IMG",
    "page": "beaches-desktop",
    "msg": "Imagem partida",
    "detail": "https://images.unsplash.com/photo-1759964711214-7b6e0243af49?crop=entropy&cs=tinysrgb&fit=max&fm=jpg&q=80&w=1080"
  },
  {
    "type": "BROKEN-IMG",
    "page": "beaches-desktop",
    "msg": "Imagem partida",
    "detail": "https://images.unsplash.com/photo-1604245891364-d2e8f2b94bbe?auto=format&fit=crop&w=1200&q=80"
  },
  {
    "type": "BROKEN-IMG",
    "page": "beaches-desktop",
    "msg": "Imagem partida",
    "detail": "https://images.unsplash.com/photo-1764077475786-03f0b0f874e6?auto=format&fit=crop&w=1200&q=80"
  },
  {
    "type": "BROKEN-IMG",
    "page": "beaches-desktop",
    "msg": "Imagem partida",
    "detail": "https://images.unsplash.com/photo-1486571698588-a2204703bec8?crop=entropy&cs=tinysrgb&fit=max&fm=jpg&q=80&w=1080"
  },
  {
    "type": "BROKEN-IMG",
    "page": "beaches-desktop",
    "msg": "Imagem partida",
    "detail": "https://images.unsplash.com/photo-1730764638413-9c22c1dc1f5c?crop=entropy&cs=tinysrgb&fit=max&fm=jpg&q=80&w=1080"
  },
  {
    "type": "BROKEN-IMG",
    "page": "beaches-desktop",
    "msg": "Imagem partida",
    "detail": "https://images.unsplash.com/photo-1644247042828-35671d6366ab?crop=entropy&cs=tinysrgb&fit=max&fm=jpg&q=80&w=1080"
  },
  {
    "type": "BROKEN-IMG",
    "page": "beaches-desktop",
    "msg": "Imagem partida",
    "detail": "https://images.unsplash.com/photo-1617040595396-28ca74b5f0e5?crop=entropy&cs=tinysrgb&fit=max&fm=jpg&q=80&w=1080"
  },
  {
    "type": "BROKEN-IMG",
    "page": "beaches-desktop",
    "msg": "Imagem partida",
    "detail": "https://images.unsplash.com/photo-1745594151312-ace72cc39f88?crop=entropy&cs=tinysrgb&fit=max&fm=jpg&q=80&w=1080"
  },
  {
    "type": "BROKEN-IMG",
    "page": "beaches-desktop",
    "msg": "Imagem partida",
    "detail": "https://images.unsplash.com/photo-1663313991553-6bb40f655023?crop=entropy&cs=tinysrgb&fit=max&fm=jpg&q=80&w=1080"
  },
  {
    "type": "BROKEN-IMG",
    "page": "beaches-desktop",
    "msg": "Imagem partida",
    "detail": "https://images.unsplash.com/photo-1745629036402-90ff542bc26e?crop=entropy&cs=tinysrgb&fit=max&fm=jpg&q=80&w=1080"
  },
  {
    "type": "BROKEN-IMG",
    "page": "beaches-desktop",
    "msg": "Imagem partida",
    "detail": "https://images.unsplash.com/photo-1549474750-8cd9887d3e47?crop=entropy&cs=tinysrgb&fit=max&fm=jpg&q=80&w=1080"
  },
  {
    "type": "BROKEN-IMG",
    "page": "beaches-desktop",
    "msg": "Imagem partida",
    "detail": "https://images.unsplash.com/photo-1584994434781-24fca0627b0d?crop=entropy&cs=tinysrgb&fit=max&fm=jpg&q=80&w=1080"
  },
  {
    "type": "BROKEN-IMG",
    "page": "beaches-desktop",
    "msg": "Imagem partida",
    "detail": "https://images.unsplash.com/photo-1706179242144-ecc50996c987?crop=entropy&cs=tinysrgb&fit=max&fm=jpg&q=80&w=1080"
  },
  {
    "type": "BROKEN-IMG",
    "page": "beaches-desktop",
    "msg": "Imagem partida",
    "detail": "https://images.unsplash.com/photo-1562760157-a1a28713c862?auto=format&fit=crop&w=1200&q=80"
  },
  {
    "type": "BROKEN-IMG",
    "page": "beaches-desktop",
    "msg": "Imagem partida",
    "detail": "https://images.unsplash.com/photo-1617041267900-821ce936e417?auto=format&fit=crop&w=1200&q=80"
  },
  {
    "type": "BROKEN-IMG",
    "page": "beaches-desktop",
    "msg": "Imagem partida",
    "detail": "https://images.unsplash.com/photo-1653771178031-2d00dd35d574?crop=entropy&cs=tinysrgb&fit=max&fm=jpg&q=80&w=1080"
  },
  {
    "type": "BROKEN-IMG",
    "page": "beaches-desktop",
    "msg": "Imagem partida",
    "detail": "https://images.unsplash.com/photo-1767772903275-443390eb7dd8?crop=entropy&cs=tinysrgb&fit=max&fm=jpg&q=80&w=1080"
  },
  {
    "type": "BROKEN-IMG",
    "page": "beaches-desktop",
    "msg": "Imagem partida",
    "detail": "https://images.unsplash.com/photo-1587973878097-ef3aabd5eeaa?auto=format&fit=crop&w=1200&q=80"
  },
  {
    "type": "BROKEN-IMG",
    "page": "beaches-desktop",
    "msg": "Imagem partida",
    "detail": "https://images.unsplash.com/photo-1700277656815-9fe0cf2a8bf9?crop=entropy&cs=tinysrgb&fit=max&fm=jpg&q=80&w=1080"
  },
  {
    "type": "BROKEN-IMG",
    "page": "beaches-desktop",
    "msg": "Imagem partida",
    "detail": "https://images.unsplash.com/photo-1635777253239-a30c19e79316?crop=entropy&cs=tinysrgb&fit=max&fm=jpg&q=80&w=1080"
  },
  {
    "type": "BROKEN-IMG",
    "page": "beaches-desktop",
    "msg": "Imagem partida",
    "detail": "https://images.unsplash.com/photo-1598534850992-5097de4a20fb?auto=format&fit=crop&w=1200&q=80"
  },
  {
    "type": "BROKEN-IMG",
    "page": "beaches-desktop",
    "msg": "Imagem partida",
    "detail": "https://images.unsplash.com/photo-1683549812226-f5904550ebf6?crop=entropy&cs=tinysrgb&fit=max&fm=jpg&q=80&w=1080"
  },
  {
    "type": "BROKEN-IMG",
    "page": "beaches-desktop",
    "msg": "Imagem partida",
    "detail": "https://images.unsplash.com/photo-1655987271145-ca500924995d?crop=entropy&cs=tinysrgb&fit=max&fm=jpg&q=80&w=1080"
  },
  {
    "type": "BROKEN-IMG",
    "page": "beaches-desktop",
    "msg": "Imagem partida",
    "detail": "https://images.unsplash.com/photo-1663602656480-c96f6f0a6f91?crop=entropy&cs=tinysrgb&fit=max&fm=jpg&q=80&w=1080"
  },
  {
    "type": "BROKEN-IMG",
    "page": "beaches-desktop",
    "msg": "Imagem partida",
    "detail": "https://images.unsplash.com/photo-1601119946691-0fb1a0b8590c?auto=format&fit=crop&w=1200&q=80"
  },
  {
    "type": "BROKEN-IMG",
    "page": "beaches-desktop",
    "msg": "Imagem partida",
    "detail": "https://images.unsplash.com/photo-1581080628455-b3be8c8b39f0?crop=entropy&cs=tinysrgb&fit=max&fm=jpg&q=80&w=1080"
  },
  {
    "type": "BROKEN-IMG",
    "page": "beaches-desktop",
    "msg": "Imagem partida",
    "detail": "https://images.unsplash.com/photo-1663602657254-b2d9a70590da?auto=format&fit=crop&w=1200&q=80"
  },
  {
    "type": "BROKEN-IMG",
    "page": "beaches-desktop",
    "msg": "Imagem partida",
    "detail": "https://images.unsplash.com/photo-1763578473047-d7d26a02ea93?crop=entropy&cs=tinysrgb&fit=max&fm=jpg&q=80&w=1080"
  },
  {
    "type": "BROKEN-IMG",
    "page": "beaches-desktop",
    "msg": "Imagem partida",
    "detail": "https://images.unsplash.com/photo-1663588694466-89df0d3e60e6?auto=format&fit=crop&w=1200&q=80"
  },
  {
    "type": "BROKEN-IMG",
    "page": "beaches-desktop",
    "msg": "Imagem partida",
    "detail": "https://images.unsplash.com/photo-1640064937825-852ac4121afc?auto=format&fit=crop&w=1200&q=80"
  },
  {
    "type": "BROKEN-IMG",
    "page": "beaches-desktop",
    "msg": "Imagem partida",
    "detail": "https://images.unsplash.com/photo-1745594207485-44bb09085691?auto=format&fit=crop&w=1200&q=80"
  },
  {
    "type": "BROKEN-IMG",
    "page": "beaches-desktop",
    "msg": "Imagem partida",
    "detail": "https://images.unsplash.com/photo-1664640896906-90304b2adc7b?auto=format&fit=crop&w=1200&q=80"
  },
  {
    "type": "BROKEN-IMG",
    "page": "beaches-desktop",
    "msg": "Imagem partida",
    "detail": "https://images.unsplash.com/photo-1631126844568-3b73c41b67d1?crop=entropy&cs=tinysrgb&fit=max&fm=jpg&q=80&w=1080"
  },
  {
    "type": "BROKEN-IMG",
    "page": "beaches-desktop",
    "msg": "Imagem partida",
    "detail": "https://images.unsplash.com/photo-1548441490-4c5d97bf0a12?auto=format&fit=crop&w=1200&q=80"
  },
  {
    "type": "BROKEN-IMG",
    "page": "beaches-desktop",
    "msg": "Imagem partida",
    "detail": "https://images.unsplash.com/photo-1762144062409-86fc8b23201c?crop=entropy&cs=tinysrgb&fit=max&fm=jpg&q=80&w=1080"
  },
  {
    "type": "BROKEN-IMG",
    "page": "beaches-desktop",
    "msg": "Imagem partida",
    "detail": "https://images.unsplash.com/photo-1772012403912-13599e06c1ca?crop=entropy&cs=tinysrgb&fit=max&fm=jpg&q=80&w=1080"
  },
  {
    "type": "BROKEN-IMG",
    "page": "beaches-desktop",
    "msg": "Imagem partida",
    "detail": "https://images.unsplash.com/photo-1724172455733-f774050a4f49?crop=entropy&cs=tinysrgb&fit=max&fm=jpg&q=80&w=1080"
  },
  {
    "type": "BROKEN-IMG",
    "page": "beaches-desktop",
    "msg": "Imagem partida",
    "detail": "https://images.unsplash.com/photo-1634071133713-37264540e43e?crop=entropy&cs=tinysrgb&fit=max&fm=jpg&q=80&w=1080"
  },
  {
    "type": "BROKEN-IMG",
    "page": "beaches-desktop",
    "msg": "Imagem partida",
    "detail": "https://images.unsplash.com/photo-1738520527536-bccf4b1ba885?auto=format&fit=crop&w=1200&q=80"
  },
  {
    "type": "BROKEN-IMG",
    "page": "beaches-desktop",
    "msg": "Imagem partida",
    "detail": "https://images.unsplash.com/photo-1639515606199-ce3e4828d525?auto=format&fit=crop&w=1200&q=80"
  },
  {
    "type": "BROKEN-IMG",
    "page": "beaches-desktop",
    "msg": "Imagem partida",
    "detail": "https://images.unsplash.com/photo-1680214075621-32cdef76681c?crop=entropy&cs=tinysrgb&fit=max&fm=jpg&q=80&w=1080"
  },
  {
    "type": "BROKEN-IMG",
    "page": "beaches-desktop",
    "msg": "Imagem partida",
    "detail": "https://images.unsplash.com/photo-1556904815-08691f9aa375?auto=format&fit=crop&w=1200&q=80"
  },
  {
    "type": "BROKEN-IMG",
    "page": "beaches-desktop",
    "msg": "Imagem partida",
    "detail": "https://images.unsplash.com/photo-1599587278555-25aea52d0765?auto=format&fit=crop&w=1200&q=80"
  },
  {
    "type": "BROKEN-IMG",
    "page": "beaches-desktop",
    "msg": "Imagem partida",
    "detail": "https://images.unsplash.com/photo-1579184410476-d4021beff617?auto=format&fit=crop&w=1200&q=80"
  },
  {
    "type": "BROKEN-IMG",
    "page": "beaches-desktop",
    "msg": "Imagem partida",
    "detail": "https://images.unsplash.com/photo-1672933914980-40663b85ed6f?crop=entropy&cs=tinysrgb&fit=max&fm=jpg&q=80&w=1080"
  },
  {
    "type": "BROKEN-IMG",
    "page": "beaches-desktop",
    "msg": "Imagem partida",
    "detail": "https://images.unsplash.com/photo-1526568717785-b530e8613bde?crop=entropy&cs=tinysrgb&fit=max&fm=jpg&q=80&w=1080"
  },
  {
    "type": "BROKEN-IMG",
    "page": "beaches-desktop",
    "msg": "Imagem partida",
    "detail": "https://images.unsplash.com/photo-1651237070396-b2dba667d883?auto=format&fit=crop&w=1200&q=80"
  },
  {
    "type": "BROKEN-IMG",
    "page": "beaches-desktop",
    "msg": "Imagem partida",
    "detail": "https://images.unsplash.com/photo-1579184410476-d4021beff617?crop=entropy&cs=tinysrgb&fit=max&fm=jpg&q=80&w=1080"
  },
  {
    "type": "BROKEN-IMG",
    "page": "beaches-desktop",
    "msg": "Imagem partida",
    "detail": "https://images.unsplash.com/photo-1745481026259-62754c61f5a2?crop=entropy&cs=tinysrgb&fit=max&fm=jpg&q=80&w=1080"
  },
  {
    "type": "BROKEN-IMG",
    "page": "beaches-desktop",
    "msg": "Imagem partida",
    "detail": "https://images.unsplash.com/photo-1726508513578-fc9fad850a3f?crop=entropy&cs=tinysrgb&fit=max&fm=jpg&q=80&w=1080"
  },
  {
    "type": "BROKEN-IMG",
    "page": "beaches-desktop",
    "msg": "Imagem partida",
    "detail": "https://images.unsplash.com/photo-1746289724690-fd134865ccc1?crop=entropy&cs=tinysrgb&fit=max&fm=jpg&q=80&w=1080"
  },
  {
    "type": "BROKEN-IMG",
    "page": "beaches-desktop",
    "msg": "Imagem partida",
    "detail": "https://images.unsplash.com/photo-1751711157233-651fc0d1806e?crop=entropy&cs=tinysrgb&fit=max&fm=jpg&q=80&w=1080"
  },
  {
    "type": "BROKEN-IMG",
    "page": "beaches-desktop",
    "msg": "Imagem partida",
    "detail": "https://images.unsplash.com/photo-1715535820232-912d4e1f000f?crop=entropy&cs=tinysrgb&fit=max&fm=jpg&q=80&w=1080"
  },
  {
    "type": "BROKEN-IMG",
    "page": "beaches-desktop",
    "msg": "Imagem partida",
    "detail": "https://images.unsplash.com/photo-1725442224865-5c653c25fdb6?crop=entropy&cs=tinysrgb&fit=max&fm=jpg&q=80&w=1080"
  },
  {
    "type": "BROKEN-IMG",
    "page": "beaches-desktop",
    "msg": "Imagem partida",
    "detail": "https://images.unsplash.com/photo-1700510517006-d8f5f6c83b3d?auto=format&fit=crop&w=1200&q=80"
  },
  {
    "type": "BROKEN-IMG",
    "page": "beaches-desktop",
    "msg": "Imagem partida",
    "detail": "https://images.unsplash.com/photo-1707340247005-3b3deebe89aa?crop=entropy&cs=tinysrgb&fit=max&fm=jpg&q=80&w=1080"
  },
  {
    "type": "BROKEN-IMG",
    "page": "beaches-desktop",
    "msg": "Imagem partida",
    "detail": "https://images.unsplash.com/photo-1583919062391-40251621ee76?crop=entropy&cs=tinysrgb&fit=max&fm=jpg&q=80&w=1080"
  },
  {
    "type": "BROKEN-IMG",
    "page": "beaches-desktop",
    "msg": "Imagem partida",
    "detail": "https://images.unsplash.com/photo-1677962555220-7138710333b0?crop=entropy&cs=tinysrgb&fit=max&fm=jpg&q=80&w=1080"
  },
  {
    "type": "BROKEN-IMG",
    "page": "beaches-desktop",
    "msg": "Imagem partida",
    "detail": "https://images.unsplash.com/photo-1635550047656-03f7b494c9c9?crop=entropy&cs=tinysrgb&fit=max&fm=jpg&q=80&w=1080"
  },
  {
    "type": "BROKEN-IMG",
    "page": "beaches-desktop",
    "msg": "Imagem partida",
    "detail": "https://images.unsplash.com/photo-1602880938195-c5aa0ebb1cba?crop=entropy&cs=tinysrgb&fit=max&fm=jpg&q=80&w=1080"
  },
  {
    "type": "CTA-NO-DEST",
    "page": "beaches-desktop",
    "msg": "CTA sem destino real: \"Limpar\"",
    "detail": ""
  },
  {
    "type": "CTA-NO-DEST",
    "page": "beaches-desktop",
    "msg": "CTA sem destino real: \"Todas\"",
    "detail": ""
  },
  {
    "type": "CTA-NO-DEST",
    "page": "beaches-desktop",
    "msg": "CTA sem destino real: \"Algarve\"",
    "detail": ""
  },
  {
    "type": "CTA-NO-DEST",
    "page": "beaches-desktop",
    "msg": "CTA sem destino real: \"Lisboa\"",
    "detail": ""
  },
  {
    "type": "CTA-NO-DEST",
    "page": "beaches-desktop",
    "msg": "CTA sem destino real: \"Porto\"",
    "detail": ""
  },
  {
    "type": "CTA-NO-DEST",
    "page": "beaches-desktop",
    "msg": "CTA sem destino real: \"Alentejo\"",
    "detail": ""
  },
  {
    "type": "CTA-NO-DEST",
    "page": "beaches-desktop",
    "msg": "CTA sem destino real: \"Madeira\"",
    "detail": ""
  },
  {
    "type": "CTA-NO-DEST",
    "page": "beaches-desktop",
    "msg": "CTA sem destino real: \"Açores\"",
    "detail": ""
  },
  {
    "type": "CTA-NO-DEST",
    "page": "beaches-desktop",
    "msg": "CTA sem destino real: \"Qualquer qualidade\"",
    "detail": ""
  },
  {
    "type": "CTA-NO-DEST",
    "page": "beaches-desktop",
    "msg": "CTA sem destino real: \"Excelente\"",
    "detail": ""
  },
  {
    "type": "CTA-NO-DEST",
    "page": "beaches-desktop",
    "msg": "CTA sem destino real: \"Boa\"",
    "detail": ""
  },
  {
    "type": "CTA-NO-DEST",
    "page": "beaches-desktop",
    "msg": "CTA sem destino real: \"Para a Família\n\nÁguas calmas, serviços de apoio e bandeira a\"",
    "detail": ""
  },
  {
    "type": "CTA-NO-DEST",
    "page": "beaches-desktop",
    "msg": "CTA sem destino real: \"Surf & Desporto\n\nOndulação consistente e atlantic swell. Cos\"",
    "detail": ""
  },
  {
    "type": "CTA-NO-DEST",
    "page": "beaches-desktop",
    "msg": "CTA sem destino real: \"Natureza & Silêncio\n\nPraias isoladas, Costa Vicentina proteg\"",
    "detail": ""
  },
  {
    "type": "CTA-NO-DEST",
    "page": "beaches-desktop",
    "msg": "CTA sem destino real: \"Melhor Qualidade\n\nFiltradas por qualidade \"Excelente\" — prai\"",
    "detail": ""
  },
  {
    "type": "CTA-NO-DEST",
    "page": "beaches-desktop",
    "msg": "CTA sem destino real: \"Buscar\"",
    "detail": ""
  },
  {
    "type": "CTA-NO-DEST",
    "page": "beaches-desktop",
    "msg": "CTA sem destino real: \"Menu\"",
    "detail": ""
  },
  {
    "type": "JS-ERROR",
    "page": "_desktop",
    "msg": "Identifier 'SUPABASE_URL' has already been declared",
    "detail": ""
  },
  {
    "type": "BROKEN-IMG",
    "page": "beach-detail-desktop",
    "msg": "Imagem partida",
    "detail": "NO-SRC"
  },
  {
    "type": "CTA-NO-DEST",
    "page": "beach-detail-desktop",
    "msg": "CTA sem destino real: \"Ver todas as praias\nIr para o Início\"",
    "detail": ""
  },
  {
    "type": "CTA-NO-DEST",
    "page": "beach-detail-desktop",
    "msg": "CTA sem destino real: \"Abrir no Google Maps\"",
    "detail": ""
  },
  {
    "type": "CTA-NO-DEST",
    "page": "beach-detail-desktop",
    "msg": "CTA sem destino real: \"Mapa\"",
    "detail": ""
  },
  {
    "type": "CTA-NO-DEST",
    "page": "beach-detail-desktop",
    "msg": "CTA sem destino real: \"Menu\"",
    "detail": ""
  },
  {
    "type": "CTA-NO-DEST",
    "page": "surf-desktop",
    "msg": "CTA sem destino real: \"Todos\"",
    "detail": ""
  },
  {
    "type": "CTA-NO-DEST",
    "page": "surf-desktop",
    "msg": "CTA sem destino real: \"Iniciante\"",
    "detail": ""
  },
  {
    "type": "CTA-NO-DEST",
    "page": "surf-desktop",
    "msg": "CTA sem destino real: \"Intermédio\"",
    "detail": ""
  },
  {
    "type": "CTA-NO-DEST",
    "page": "surf-desktop",
    "msg": "CTA sem destino real: \"Avançado\"",
    "detail": ""
  },
  {
    "type": "CTA-NO-DEST",
    "page": "surf-desktop",
    "msg": "CTA sem destino real: \"Profissional\"",
    "detail": ""
  },
  {
    "type": "CTA-NO-DEST",
    "page": "surf-desktop",
    "msg": "CTA sem destino real: \"Todas as Regiões\"",
    "detail": ""
  },
  {
    "type": "CTA-NO-DEST",
    "page": "surf-desktop",
    "msg": "CTA sem destino real: \"Porto\"",
    "detail": ""
  },
  {
    "type": "CTA-NO-DEST",
    "page": "surf-desktop",
    "msg": "CTA sem destino real: \"Centro\"",
    "detail": ""
  },
  {
    "type": "CTA-NO-DEST",
    "page": "surf-desktop",
    "msg": "CTA sem destino real: \"Lisboa\"",
    "detail": ""
  },
  {
    "type": "CTA-NO-DEST",
    "page": "surf-desktop",
    "msg": "CTA sem destino real: \"Alentejo\"",
    "detail": ""
  },
  {
    "type": "CTA-NO-DEST",
    "page": "surf-desktop",
    "msg": "CTA sem destino real: \"Algarve\"",
    "detail": ""
  },
  {
    "type": "CTA-NO-DEST",
    "page": "surf-desktop",
    "msg": "CTA sem destino real: \"Açores\"",
    "detail": ""
  },
  {
    "type": "CTA-NO-DEST",
    "page": "surf-desktop",
    "msg": "CTA sem destino real: \"Quando é a melhor época para surfar em Portugal?\"",
    "detail": ""
  },
  {
    "type": "CTA-NO-DEST",
    "page": "surf-desktop",
    "msg": "CTA sem destino real: \"Qual o spot mais adequado para principiantes?\"",
    "detail": ""
  },
  {
    "type": "CTA-NO-DEST",
    "page": "surf-desktop",
    "msg": "CTA sem destino real: \"É necessário saber nadar para aprender surf?\"",
    "detail": ""
  },
  {
    "type": "CTA-NO-DEST",
    "page": "surf-desktop",
    "msg": "CTA sem destino real: \"Qual o equipamento básico necessário?\"",
    "detail": ""
  },
  {
    "type": "CTA-NO-DEST",
    "page": "surf-desktop",
    "msg": "CTA sem destino real: \"Posso surfar em Portugal durante todo o ano?\"",
    "detail": ""
  },
  {
    "type": "CTA-NO-DEST",
    "page": "surf-desktop",
    "msg": "CTA sem destino real: \"Quanto custa uma aula de surf em Portugal?\"",
    "detail": ""
  },
  {
    "type": "CTA-NO-DEST",
    "page": "surf-desktop",
    "msg": "CTA sem destino real: \"É perigoso surfar em Portugal para iniciantes?\"",
    "detail": ""
  },
  {
    "type": "CTA-NO-DEST",
    "page": "surf-desktop",
    "msg": "CTA sem destino real: \"Menu\"",
    "detail": ""
  },
  {
    "type": "JS-ERROR",
    "page": "_desktop",
    "msg": "Identifier 'SUPABASE_URL' has already been declared",
    "detail": ""
  },
  {
    "type": "JS-ERROR",
    "page": "_desktop",
    "msg": "Identifier 'SUPABASE_URL' has already been declared",
    "detail": ""
  },
  {
    "type": "CTA-NO-DEST",
    "page": "precos-desktop",
    "msg": "CTA sem destino real: \"Posso cancelar a qualquer momento?\"",
    "detail": ""
  },
  {
    "type": "CTA-NO-DEST",
    "page": "precos-desktop",
    "msg": "CTA sem destino real: \"O que acontece aos meus dados se cancelar?\"",
    "detail": ""
  },
  {
    "type": "CTA-NO-DEST",
    "page": "precos-desktop",
    "msg": "CTA sem destino real: \"Existe uma versão de teste gratuita do plano Pro?\"",
    "detail": ""
  },
  {
    "type": "CTA-NO-DEST",
    "page": "precos-desktop",
    "msg": "CTA sem destino real: \"O desconto anual aplica-se imediatamente?\"",
    "detail": ""
  },
  {
    "type": "CTA-NO-DEST",
    "page": "precos-desktop",
    "msg": "CTA sem destino real: \"O plano Partner serve para que tipo de negócios?\"",
    "detail": ""
  },
  {
    "type": "CTA-NO-DEST",
    "page": "precos-desktop",
    "msg": "CTA sem destino real: \"Como funciona a API de condições para parceiros?\"",
    "detail": ""
  },
  {
    "type": "CTA-NO-DEST",
    "page": "precos-desktop",
    "msg": "CTA sem destino real: \"Qual a diferença entre o plano Partner e a parceria completa\"",
    "detail": ""
  },
  {
    "type": "CTA-NO-DEST",
    "page": "parceiros-desktop",
    "msg": "CTA sem destino real: \"Submeter candidatura\"",
    "detail": ""
  },
  {
    "type": "JS-ERROR",
    "page": "_desktop",
    "msg": "Identifier 'SUPABASE_URL' has already been declared",
    "detail": ""
  },
  {
    "type": "CTA-NO-DEST",
    "page": "contact-desktop",
    "msg": "CTA sem destino real: \"Enviar Mensagem\"",
    "detail": ""
  },
  {
    "type": "CTA-NO-DEST",
    "page": "contact-desktop",
    "msg": "CTA sem destino real: \"Como me candidato a parceiro do portal?\"",
    "detail": ""
  },
  {
    "type": "CTA-NO-DEST",
    "page": "contact-desktop",
    "msg": "CTA sem destino real: \"Como funciona o serviço de planeamento de viagens?\"",
    "detail": ""
  },
  {
    "type": "CTA-NO-DEST",
    "page": "contact-desktop",
    "msg": "CTA sem destino real: \"Como posso sugerir uma praia que não está na plataforma?\"",
    "detail": ""
  },
  {
    "type": "CTA-NO-DEST",
    "page": "contact-desktop",
    "msg": "CTA sem destino real: \"Em quanto tempo recebo uma resposta?\"",
    "detail": ""
  },
  {
    "type": "CTA-NO-DEST",
    "page": "contact-desktop",
    "msg": "CTA sem destino real: \"Trabalham com imprensa e media?\"",
    "detail": ""
  },
  {
    "type": "BROKEN-IMG",
    "page": "homepage-mobile",
    "msg": "Imagem partida",
    "detail": "https://images.unsplash.com/photo-1584994434781-24fca0627b0d?crop=entropy&cs=tinysrgb&fit=max&fm=jpg&q=80&w=1080"
  },
  {
    "type": "BROKEN-IMG",
    "page": "homepage-mobile",
    "msg": "Imagem partida",
    "detail": "https://images.unsplash.com/photo-1635777253239-a30c19e79316?crop=entropy&cs=tinysrgb&fit=max&fm=jpg&q=80&w=1080"
  },
  {
    "type": "BROKEN-IMG",
    "page": "homepage-mobile",
    "msg": "Imagem partida",
    "detail": "https://images.unsplash.com/photo-1598534850992-5097de4a20fb?auto=format&fit=crop&w=1200&q=80"
  },
  {
    "type": "BROKEN-IMG",
    "page": "homepage-mobile",
    "msg": "Imagem partida",
    "detail": "https://images.unsplash.com/photo-1683549812226-f5904550ebf6?crop=entropy&cs=tinysrgb&fit=max&fm=jpg&q=80&w=1080"
  },
  {
    "type": "BROKEN-IMG",
    "page": "homepage-mobile",
    "msg": "Imagem partida",
    "detail": "https://images.unsplash.com/photo-1663602656480-c96f6f0a6f91?crop=entropy&cs=tinysrgb&fit=max&fm=jpg&q=80&w=1080"
  },
  {
    "type": "BROKEN-IMG",
    "page": "homepage-mobile",
    "msg": "Imagem partida",
    "detail": "https://images.unsplash.com/photo-1663313991553-6bb40f655023?crop=entropy&cs=tinysrgb&fit=max&fm=jpg&q=80&w=1080"
  },
  {
    "type": "CTA-NO-DEST",
    "page": "homepage-mobile",
    "msg": "CTA sem destino real: \"Ver Alojamento\"",
    "detail": ""
  },
  {
    "type": "CTA-NO-DEST",
    "page": "homepage-mobile",
    "msg": "CTA sem destino real: \"Ver Experiências\"",
    "detail": ""
  },
  {
    "type": "CTA-NO-DEST",
    "page": "homepage-mobile",
    "msg": "CTA sem destino real: \"Ver Equipamento\"",
    "detail": ""
  },
  {
    "type": "BROKEN-IMG",
    "page": "beaches-mobile",
    "msg": "Imagem partida",
    "detail": "https://images.unsplash.com/photo-1762814407325-1c7548365c84?crop=entropy&cs=tinysrgb&fit=max&fm=jpg&q=80&w=1080"
  },
  {
    "type": "BROKEN-IMG",
    "page": "beaches-mobile",
    "msg": "Imagem partida",
    "detail": "https://images.unsplash.com/photo-1720351454314-6209b5e2a031?crop=entropy&cs=tinysrgb&fit=max&fm=jpg&q=80&w=1080"
  },
  {
    "type": "BROKEN-IMG",
    "page": "beaches-mobile",
    "msg": "Imagem partida",
    "detail": "https://images.unsplash.com/photo-1764077299993-fba51e858b03?crop=entropy&cs=tinysrgb&fit=max&fm=jpg&q=80&w=1080"
  },
  {
    "type": "BROKEN-IMG",
    "page": "beaches-mobile",
    "msg": "Imagem partida",
    "detail": "https://images.unsplash.com/photo-1602327692112-7e593fd83dd1?crop=entropy&cs=tinysrgb&fit=max&fm=jpg&q=80&w=1080"
  },
  {
    "type": "BROKEN-IMG",
    "page": "beaches-mobile",
    "msg": "Imagem partida",
    "detail": "https://images.unsplash.com/photo-1565636167429-7ceb7f007a0a?crop=entropy&cs=tinysrgb&fit=max&fm=jpg&q=80&w=1080"
  },
  {
    "type": "BROKEN-IMG",
    "page": "beaches-mobile",
    "msg": "Imagem partida",
    "detail": "https://images.unsplash.com/photo-1756661433934-b30c5353af2e?crop=entropy&cs=tinysrgb&fit=max&fm=jpg&q=80&w=1080"
  },
  {
    "type": "BROKEN-IMG",
    "page": "beaches-mobile",
    "msg": "Imagem partida",
    "detail": "https://images.unsplash.com/photo-1542413965-e786216dfcd9?auto=format&fit=crop&w=1200&q=80"
  },
  {
    "type": "BROKEN-IMG",
    "page": "beaches-mobile",
    "msg": "Imagem partida",
    "detail": "https://images.unsplash.com/photo-1721365240263-ba54a74d478d?auto=format&fit=crop&w=1200&q=80"
  },
  {
    "type": "BROKEN-IMG",
    "page": "beaches-mobile",
    "msg": "Imagem partida",
    "detail": "https://images.unsplash.com/photo-1675112747580-56d36def89f3?crop=entropy&cs=tinysrgb&fit=max&fm=jpg&q=80&w=1080"
  },
  {
    "type": "BROKEN-IMG",
    "page": "beaches-mobile",
    "msg": "Imagem partida",
    "detail": "https://images.unsplash.com/photo-1501928273014-b17d1c641913?crop=entropy&cs=tinysrgb&fit=max&fm=jpg&q=80&w=1080"
  },
  {
    "type": "BROKEN-IMG",
    "page": "beaches-mobile",
    "msg": "Imagem partida",
    "detail": "https://images.unsplash.com/photo-1615476412193-95cbf08ae2b2?auto=format&fit=crop&w=1200&q=80"
  },
  {
    "type": "BROKEN-IMG",
    "page": "beaches-mobile",
    "msg": "Imagem partida",
    "detail": "https://images.unsplash.com/photo-1617277775103-58f6f6cf980c?crop=entropy&cs=tinysrgb&fit=max&fm=jpg&q=80&w=1080"
  },
  {
    "type": "BROKEN-IMG",
    "page": "beaches-mobile",
    "msg": "Imagem partida",
    "detail": "https://images.unsplash.com/photo-1674585714925-c096ba706a97?crop=entropy&cs=tinysrgb&fit=max&fm=jpg&q=80&w=1080"
  },
  {
    "type": "BROKEN-IMG",
    "page": "beaches-mobile",
    "msg": "Imagem partida",
    "detail": "https://images.unsplash.com/photo-1681297158191-bab1ed61fbbf?crop=entropy&cs=tinysrgb&fit=max&fm=jpg&q=80&w=1080"
  },
  {
    "type": "BROKEN-IMG",
    "page": "beaches-mobile",
    "msg": "Imagem partida",
    "detail": "https://images.unsplash.com/photo-1635619608953-b6eb0bf24bba?crop=entropy&cs=tinysrgb&fit=max&fm=jpg&q=80&w=1080"
  },
  {
    "type": "BROKEN-IMG",
    "page": "beaches-mobile",
    "msg": "Imagem partida",
    "detail": "https://images.unsplash.com/photo-1651237031934-4c1c78b9f1ba?auto=format&fit=crop&w=1200&q=80"
  },
  {
    "type": "BROKEN-IMG",
    "page": "beaches-mobile",
    "msg": "Imagem partida",
    "detail": "https://images.unsplash.com/photo-1759964711214-7b6e0243af49?crop=entropy&cs=tinysrgb&fit=max&fm=jpg&q=80&w=1080"
  },
  {
    "type": "BROKEN-IMG",
    "page": "beaches-mobile",
    "msg": "Imagem partida",
    "detail": "https://images.unsplash.com/photo-1604245891364-d2e8f2b94bbe?auto=format&fit=crop&w=1200&q=80"
  },
  {
    "type": "BROKEN-IMG",
    "page": "beaches-mobile",
    "msg": "Imagem partida",
    "detail": "https://images.unsplash.com/photo-1764077475786-03f0b0f874e6?auto=format&fit=crop&w=1200&q=80"
  },
  {
    "type": "BROKEN-IMG",
    "page": "beaches-mobile",
    "msg": "Imagem partida",
    "detail": "https://images.unsplash.com/photo-1486571698588-a2204703bec8?crop=entropy&cs=tinysrgb&fit=max&fm=jpg&q=80&w=1080"
  },
  {
    "type": "BROKEN-IMG",
    "page": "beaches-mobile",
    "msg": "Imagem partida",
    "detail": "https://images.unsplash.com/photo-1730764638413-9c22c1dc1f5c?crop=entropy&cs=tinysrgb&fit=max&fm=jpg&q=80&w=1080"
  },
  {
    "type": "BROKEN-IMG",
    "page": "beaches-mobile",
    "msg": "Imagem partida",
    "detail": "https://images.unsplash.com/photo-1644247042828-35671d6366ab?crop=entropy&cs=tinysrgb&fit=max&fm=jpg&q=80&w=1080"
  },
  {
    "type": "BROKEN-IMG",
    "page": "beaches-mobile",
    "msg": "Imagem partida",
    "detail": "https://images.unsplash.com/photo-1617040595396-28ca74b5f0e5?crop=entropy&cs=tinysrgb&fit=max&fm=jpg&q=80&w=1080"
  },
  {
    "type": "BROKEN-IMG",
    "page": "beaches-mobile",
    "msg": "Imagem partida",
    "detail": "https://images.unsplash.com/photo-1745594151312-ace72cc39f88?crop=entropy&cs=tinysrgb&fit=max&fm=jpg&q=80&w=1080"
  },
  {
    "type": "BROKEN-IMG",
    "page": "beaches-mobile",
    "msg": "Imagem partida",
    "detail": "https://images.unsplash.com/photo-1663313991553-6bb40f655023?crop=entropy&cs=tinysrgb&fit=max&fm=jpg&q=80&w=1080"
  },
  {
    "type": "BROKEN-IMG",
    "page": "beaches-mobile",
    "msg": "Imagem partida",
    "detail": "https://images.unsplash.com/photo-1745629036402-90ff542bc26e?crop=entropy&cs=tinysrgb&fit=max&fm=jpg&q=80&w=1080"
  },
  {
    "type": "BROKEN-IMG",
    "page": "beaches-mobile",
    "msg": "Imagem partida",
    "detail": "https://images.unsplash.com/photo-1549474750-8cd9887d3e47?crop=entropy&cs=tinysrgb&fit=max&fm=jpg&q=80&w=1080"
  },
  {
    "type": "BROKEN-IMG",
    "page": "beaches-mobile",
    "msg": "Imagem partida",
    "detail": "https://images.unsplash.com/photo-1584994434781-24fca0627b0d?crop=entropy&cs=tinysrgb&fit=max&fm=jpg&q=80&w=1080"
  },
  {
    "type": "BROKEN-IMG",
    "page": "beaches-mobile",
    "msg": "Imagem partida",
    "detail": "https://images.unsplash.com/photo-1706179242144-ecc50996c987?crop=entropy&cs=tinysrgb&fit=max&fm=jpg&q=80&w=1080"
  },
  {
    "type": "BROKEN-IMG",
    "page": "beaches-mobile",
    "msg": "Imagem partida",
    "detail": "https://images.unsplash.com/photo-1562760157-a1a28713c862?auto=format&fit=crop&w=1200&q=80"
  },
  {
    "type": "BROKEN-IMG",
    "page": "beaches-mobile",
    "msg": "Imagem partida",
    "detail": "https://images.unsplash.com/photo-1617041267900-821ce936e417?auto=format&fit=crop&w=1200&q=80"
  },
  {
    "type": "BROKEN-IMG",
    "page": "beaches-mobile",
    "msg": "Imagem partida",
    "detail": "https://images.unsplash.com/photo-1653771178031-2d00dd35d574?crop=entropy&cs=tinysrgb&fit=max&fm=jpg&q=80&w=1080"
  },
  {
    "type": "BROKEN-IMG",
    "page": "beaches-mobile",
    "msg": "Imagem partida",
    "detail": "https://images.unsplash.com/photo-1767772903275-443390eb7dd8?crop=entropy&cs=tinysrgb&fit=max&fm=jpg&q=80&w=1080"
  },
  {
    "type": "BROKEN-IMG",
    "page": "beaches-mobile",
    "msg": "Imagem partida",
    "detail": "https://images.unsplash.com/photo-1587973878097-ef3aabd5eeaa?auto=format&fit=crop&w=1200&q=80"
  },
  {
    "type": "BROKEN-IMG",
    "page": "beaches-mobile",
    "msg": "Imagem partida",
    "detail": "https://images.unsplash.com/photo-1700277656815-9fe0cf2a8bf9?crop=entropy&cs=tinysrgb&fit=max&fm=jpg&q=80&w=1080"
  },
  {
    "type": "BROKEN-IMG",
    "page": "beaches-mobile",
    "msg": "Imagem partida",
    "detail": "https://images.unsplash.com/photo-1635777253239-a30c19e79316?crop=entropy&cs=tinysrgb&fit=max&fm=jpg&q=80&w=1080"
  },
  {
    "type": "BROKEN-IMG",
    "page": "beaches-mobile",
    "msg": "Imagem partida",
    "detail": "https://images.unsplash.com/photo-1598534850992-5097de4a20fb?auto=format&fit=crop&w=1200&q=80"
  },
  {
    "type": "BROKEN-IMG",
    "page": "beaches-mobile",
    "msg": "Imagem partida",
    "detail": "https://images.unsplash.com/photo-1683549812226-f5904550ebf6?crop=entropy&cs=tinysrgb&fit=max&fm=jpg&q=80&w=1080"
  },
  {
    "type": "BROKEN-IMG",
    "page": "beaches-mobile",
    "msg": "Imagem partida",
    "detail": "https://images.unsplash.com/photo-1655987271145-ca500924995d?crop=entropy&cs=tinysrgb&fit=max&fm=jpg&q=80&w=1080"
  },
  {
    "type": "BROKEN-IMG",
    "page": "beaches-mobile",
    "msg": "Imagem partida",
    "detail": "https://images.unsplash.com/photo-1663602656480-c96f6f0a6f91?crop=entropy&cs=tinysrgb&fit=max&fm=jpg&q=80&w=1080"
  },
  {
    "type": "BROKEN-IMG",
    "page": "beaches-mobile",
    "msg": "Imagem partida",
    "detail": "https://images.unsplash.com/photo-1601119946691-0fb1a0b8590c?auto=format&fit=crop&w=1200&q=80"
  },
  {
    "type": "BROKEN-IMG",
    "page": "beaches-mobile",
    "msg": "Imagem partida",
    "detail": "https://images.unsplash.com/photo-1581080628455-b3be8c8b39f0?crop=entropy&cs=tinysrgb&fit=max&fm=jpg&q=80&w=1080"
  },
  {
    "type": "BROKEN-IMG",
    "page": "beaches-mobile",
    "msg": "Imagem partida",
    "detail": "https://images.unsplash.com/photo-1663602657254-b2d9a70590da?auto=format&fit=crop&w=1200&q=80"
  },
  {
    "type": "BROKEN-IMG",
    "page": "beaches-mobile",
    "msg": "Imagem partida",
    "detail": "https://images.unsplash.com/photo-1763578473047-d7d26a02ea93?crop=entropy&cs=tinysrgb&fit=max&fm=jpg&q=80&w=1080"
  },
  {
    "type": "BROKEN-IMG",
    "page": "beaches-mobile",
    "msg": "Imagem partida",
    "detail": "https://images.unsplash.com/photo-1663588694466-89df0d3e60e6?auto=format&fit=crop&w=1200&q=80"
  },
  {
    "type": "BROKEN-IMG",
    "page": "beaches-mobile",
    "msg": "Imagem partida",
    "detail": "https://images.unsplash.com/photo-1640064937825-852ac4121afc?auto=format&fit=crop&w=1200&q=80"
  },
  {
    "type": "BROKEN-IMG",
    "page": "beaches-mobile",
    "msg": "Imagem partida",
    "detail": "https://images.unsplash.com/photo-1745594207485-44bb09085691?auto=format&fit=crop&w=1200&q=80"
  },
  {
    "type": "BROKEN-IMG",
    "page": "beaches-mobile",
    "msg": "Imagem partida",
    "detail": "https://images.unsplash.com/photo-1664640896906-90304b2adc7b?auto=format&fit=crop&w=1200&q=80"
  },
  {
    "type": "BROKEN-IMG",
    "page": "beaches-mobile",
    "msg": "Imagem partida",
    "detail": "https://images.unsplash.com/photo-1631126844568-3b73c41b67d1?crop=entropy&cs=tinysrgb&fit=max&fm=jpg&q=80&w=1080"
  },
  {
    "type": "BROKEN-IMG",
    "page": "beaches-mobile",
    "msg": "Imagem partida",
    "detail": "https://images.unsplash.com/photo-1548441490-4c5d97bf0a12?auto=format&fit=crop&w=1200&q=80"
  },
  {
    "type": "BROKEN-IMG",
    "page": "beaches-mobile",
    "msg": "Imagem partida",
    "detail": "https://images.unsplash.com/photo-1762144062409-86fc8b23201c?crop=entropy&cs=tinysrgb&fit=max&fm=jpg&q=80&w=1080"
  },
  {
    "type": "BROKEN-IMG",
    "page": "beaches-mobile",
    "msg": "Imagem partida",
    "detail": "https://images.unsplash.com/photo-1772012403912-13599e06c1ca?crop=entropy&cs=tinysrgb&fit=max&fm=jpg&q=80&w=1080"
  },
  {
    "type": "BROKEN-IMG",
    "page": "beaches-mobile",
    "msg": "Imagem partida",
    "detail": "https://images.unsplash.com/photo-1724172455733-f774050a4f49?crop=entropy&cs=tinysrgb&fit=max&fm=jpg&q=80&w=1080"
  },
  {
    "type": "BROKEN-IMG",
    "page": "beaches-mobile",
    "msg": "Imagem partida",
    "detail": "https://images.unsplash.com/photo-1634071133713-37264540e43e?crop=entropy&cs=tinysrgb&fit=max&fm=jpg&q=80&w=1080"
  },
  {
    "type": "BROKEN-IMG",
    "page": "beaches-mobile",
    "msg": "Imagem partida",
    "detail": "https://images.unsplash.com/photo-1738520527536-bccf4b1ba885?auto=format&fit=crop&w=1200&q=80"
  },
  {
    "type": "BROKEN-IMG",
    "page": "beaches-mobile",
    "msg": "Imagem partida",
    "detail": "https://images.unsplash.com/photo-1639515606199-ce3e4828d525?auto=format&fit=crop&w=1200&q=80"
  },
  {
    "type": "BROKEN-IMG",
    "page": "beaches-mobile",
    "msg": "Imagem partida",
    "detail": "https://images.unsplash.com/photo-1680214075621-32cdef76681c?crop=entropy&cs=tinysrgb&fit=max&fm=jpg&q=80&w=1080"
  },
  {
    "type": "BROKEN-IMG",
    "page": "beaches-mobile",
    "msg": "Imagem partida",
    "detail": "https://images.unsplash.com/photo-1556904815-08691f9aa375?auto=format&fit=crop&w=1200&q=80"
  },
  {
    "type": "BROKEN-IMG",
    "page": "beaches-mobile",
    "msg": "Imagem partida",
    "detail": "https://images.unsplash.com/photo-1599587278555-25aea52d0765?auto=format&fit=crop&w=1200&q=80"
  },
  {
    "type": "BROKEN-IMG",
    "page": "beaches-mobile",
    "msg": "Imagem partida",
    "detail": "https://images.unsplash.com/photo-1579184410476-d4021beff617?auto=format&fit=crop&w=1200&q=80"
  },
  {
    "type": "BROKEN-IMG",
    "page": "beaches-mobile",
    "msg": "Imagem partida",
    "detail": "https://images.unsplash.com/photo-1672933914980-40663b85ed6f?crop=entropy&cs=tinysrgb&fit=max&fm=jpg&q=80&w=1080"
  },
  {
    "type": "BROKEN-IMG",
    "page": "beaches-mobile",
    "msg": "Imagem partida",
    "detail": "https://images.unsplash.com/photo-1526568717785-b530e8613bde?crop=entropy&cs=tinysrgb&fit=max&fm=jpg&q=80&w=1080"
  },
  {
    "type": "BROKEN-IMG",
    "page": "beaches-mobile",
    "msg": "Imagem partida",
    "detail": "https://images.unsplash.com/photo-1651237070396-b2dba667d883?auto=format&fit=crop&w=1200&q=80"
  },
  {
    "type": "BROKEN-IMG",
    "page": "beaches-mobile",
    "msg": "Imagem partida",
    "detail": "https://images.unsplash.com/photo-1579184410476-d4021beff617?crop=entropy&cs=tinysrgb&fit=max&fm=jpg&q=80&w=1080"
  },
  {
    "type": "BROKEN-IMG",
    "page": "beaches-mobile",
    "msg": "Imagem partida",
    "detail": "https://images.unsplash.com/photo-1745481026259-62754c61f5a2?crop=entropy&cs=tinysrgb&fit=max&fm=jpg&q=80&w=1080"
  },
  {
    "type": "BROKEN-IMG",
    "page": "beaches-mobile",
    "msg": "Imagem partida",
    "detail": "https://images.unsplash.com/photo-1726508513578-fc9fad850a3f?crop=entropy&cs=tinysrgb&fit=max&fm=jpg&q=80&w=1080"
  },
  {
    "type": "BROKEN-IMG",
    "page": "beaches-mobile",
    "msg": "Imagem partida",
    "detail": "https://images.unsplash.com/photo-1746289724690-fd134865ccc1?crop=entropy&cs=tinysrgb&fit=max&fm=jpg&q=80&w=1080"
  },
  {
    "type": "BROKEN-IMG",
    "page": "beaches-mobile",
    "msg": "Imagem partida",
    "detail": "https://images.unsplash.com/photo-1751711157233-651fc0d1806e?crop=entropy&cs=tinysrgb&fit=max&fm=jpg&q=80&w=1080"
  },
  {
    "type": "BROKEN-IMG",
    "page": "beaches-mobile",
    "msg": "Imagem partida",
    "detail": "https://images.unsplash.com/photo-1715535820232-912d4e1f000f?crop=entropy&cs=tinysrgb&fit=max&fm=jpg&q=80&w=1080"
  },
  {
    "type": "BROKEN-IMG",
    "page": "beaches-mobile",
    "msg": "Imagem partida",
    "detail": "https://images.unsplash.com/photo-1725442224865-5c653c25fdb6?crop=entropy&cs=tinysrgb&fit=max&fm=jpg&q=80&w=1080"
  },
  {
    "type": "BROKEN-IMG",
    "page": "beaches-mobile",
    "msg": "Imagem partida",
    "detail": "https://images.unsplash.com/photo-1700510517006-d8f5f6c83b3d?auto=format&fit=crop&w=1200&q=80"
  },
  {
    "type": "BROKEN-IMG",
    "page": "beaches-mobile",
    "msg": "Imagem partida",
    "detail": "https://images.unsplash.com/photo-1707340247005-3b3deebe89aa?crop=entropy&cs=tinysrgb&fit=max&fm=jpg&q=80&w=1080"
  },
  {
    "type": "BROKEN-IMG",
    "page": "beaches-mobile",
    "msg": "Imagem partida",
    "detail": "https://images.unsplash.com/photo-1583919062391-40251621ee76?crop=entropy&cs=tinysrgb&fit=max&fm=jpg&q=80&w=1080"
  },
  {
    "type": "BROKEN-IMG",
    "page": "beaches-mobile",
    "msg": "Imagem partida",
    "detail": "https://images.unsplash.com/photo-1677962555220-7138710333b0?crop=entropy&cs=tinysrgb&fit=max&fm=jpg&q=80&w=1080"
  },
  {
    "type": "BROKEN-IMG",
    "page": "beaches-mobile",
    "msg": "Imagem partida",
    "detail": "https://images.unsplash.com/photo-1635550047656-03f7b494c9c9?crop=entropy&cs=tinysrgb&fit=max&fm=jpg&q=80&w=1080"
  },
  {
    "type": "BROKEN-IMG",
    "page": "beaches-mobile",
    "msg": "Imagem partida",
    "detail": "https://images.unsplash.com/photo-1602880938195-c5aa0ebb1cba?crop=entropy&cs=tinysrgb&fit=max&fm=jpg&q=80&w=1080"
  },
  {
    "type": "CTA-NO-DEST",
    "page": "beaches-mobile",
    "msg": "CTA sem destino real: \"Limpar\"",
    "detail": ""
  },
  {
    "type": "CTA-NO-DEST",
    "page": "beaches-mobile",
    "msg": "CTA sem destino real: \"Todas\"",
    "detail": ""
  },
  {
    "type": "CTA-NO-DEST",
    "page": "beaches-mobile",
    "msg": "CTA sem destino real: \"Algarve\"",
    "detail": ""
  },
  {
    "type": "CTA-NO-DEST",
    "page": "beaches-mobile",
    "msg": "CTA sem destino real: \"Lisboa\"",
    "detail": ""
  },
  {
    "type": "CTA-NO-DEST",
    "page": "beaches-mobile",
    "msg": "CTA sem destino real: \"Porto\"",
    "detail": ""
  },
  {
    "type": "CTA-NO-DEST",
    "page": "beaches-mobile",
    "msg": "CTA sem destino real: \"Alentejo\"",
    "detail": ""
  },
  {
    "type": "CTA-NO-DEST",
    "page": "beaches-mobile",
    "msg": "CTA sem destino real: \"Madeira\"",
    "detail": ""
  },
  {
    "type": "CTA-NO-DEST",
    "page": "beaches-mobile",
    "msg": "CTA sem destino real: \"Açores\"",
    "detail": ""
  },
  {
    "type": "CTA-NO-DEST",
    "page": "beaches-mobile",
    "msg": "CTA sem destino real: \"Qualquer qualidade\"",
    "detail": ""
  },
  {
    "type": "CTA-NO-DEST",
    "page": "beaches-mobile",
    "msg": "CTA sem destino real: \"Excelente\"",
    "detail": ""
  },
  {
    "type": "CTA-NO-DEST",
    "page": "beaches-mobile",
    "msg": "CTA sem destino real: \"Boa\"",
    "detail": ""
  },
  {
    "type": "CTA-NO-DEST",
    "page": "beaches-mobile",
    "msg": "CTA sem destino real: \"Para a Família\n\nÁguas calmas, serviços de apoio e bandeira a\"",
    "detail": ""
  },
  {
    "type": "CTA-NO-DEST",
    "page": "beaches-mobile",
    "msg": "CTA sem destino real: \"Surf & Desporto\n\nOndulação consistente e atlantic swell. Cos\"",
    "detail": ""
  },
  {
    "type": "CTA-NO-DEST",
    "page": "beaches-mobile",
    "msg": "CTA sem destino real: \"Natureza & Silêncio\n\nPraias isoladas, Costa Vicentina proteg\"",
    "detail": ""
  },
  {
    "type": "CTA-NO-DEST",
    "page": "beaches-mobile",
    "msg": "CTA sem destino real: \"Melhor Qualidade\n\nFiltradas por qualidade \"Excelente\" — prai\"",
    "detail": ""
  },
  {
    "type": "CTA-NO-DEST",
    "page": "beaches-mobile",
    "msg": "CTA sem destino real: \"BUSCAR\"",
    "detail": ""
  },
  {
    "type": "CTA-NO-DEST",
    "page": "beaches-mobile",
    "msg": "CTA sem destino real: \"MENU\"",
    "detail": ""
  },
  {
    "type": "JS-ERROR",
    "page": "_mobile",
    "msg": "Identifier 'SUPABASE_URL' has already been declared",
    "detail": ""
  },
  {
    "type": "BROKEN-IMG",
    "page": "beach-detail-mobile",
    "msg": "Imagem partida",
    "detail": "NO-SRC"
  },
  {
    "type": "CTA-NO-DEST",
    "page": "beach-detail-mobile",
    "msg": "CTA sem destino real: \"Ver todas as praias\nIr para o Início\"",
    "detail": ""
  },
  {
    "type": "CTA-NO-DEST",
    "page": "beach-detail-mobile",
    "msg": "CTA sem destino real: \"Abrir no Google Maps\"",
    "detail": ""
  },
  {
    "type": "CTA-NO-DEST",
    "page": "beach-detail-mobile",
    "msg": "CTA sem destino real: \"MAPA\"",
    "detail": ""
  },
  {
    "type": "CTA-NO-DEST",
    "page": "beach-detail-mobile",
    "msg": "CTA sem destino real: \"MENU\"",
    "detail": ""
  },
  {
    "type": "CTA-NO-DEST",
    "page": "surf-mobile",
    "msg": "CTA sem destino real: \"Todos\"",
    "detail": ""
  },
  {
    "type": "CTA-NO-DEST",
    "page": "surf-mobile",
    "msg": "CTA sem destino real: \"Iniciante\"",
    "detail": ""
  },
  {
    "type": "CTA-NO-DEST",
    "page": "surf-mobile",
    "msg": "CTA sem destino real: \"Intermédio\"",
    "detail": ""
  },
  {
    "type": "CTA-NO-DEST",
    "page": "surf-mobile",
    "msg": "CTA sem destino real: \"Avançado\"",
    "detail": ""
  },
  {
    "type": "CTA-NO-DEST",
    "page": "surf-mobile",
    "msg": "CTA sem destino real: \"Profissional\"",
    "detail": ""
  },
  {
    "type": "CTA-NO-DEST",
    "page": "surf-mobile",
    "msg": "CTA sem destino real: \"Todas as Regiões\"",
    "detail": ""
  },
  {
    "type": "CTA-NO-DEST",
    "page": "surf-mobile",
    "msg": "CTA sem destino real: \"Porto\"",
    "detail": ""
  },
  {
    "type": "CTA-NO-DEST",
    "page": "surf-mobile",
    "msg": "CTA sem destino real: \"Centro\"",
    "detail": ""
  },
  {
    "type": "CTA-NO-DEST",
    "page": "surf-mobile",
    "msg": "CTA sem destino real: \"Lisboa\"",
    "detail": ""
  },
  {
    "type": "CTA-NO-DEST",
    "page": "surf-mobile",
    "msg": "CTA sem destino real: \"Alentejo\"",
    "detail": ""
  },
  {
    "type": "CTA-NO-DEST",
    "page": "surf-mobile",
    "msg": "CTA sem destino real: \"Algarve\"",
    "detail": ""
  },
  {
    "type": "CTA-NO-DEST",
    "page": "surf-mobile",
    "msg": "CTA sem destino real: \"Açores\"",
    "detail": ""
  },
  {
    "type": "CTA-NO-DEST",
    "page": "surf-mobile",
    "msg": "CTA sem destino real: \"Quando é a melhor época para surfar em Portugal?\"",
    "detail": ""
  },
  {
    "type": "CTA-NO-DEST",
    "page": "surf-mobile",
    "msg": "CTA sem destino real: \"Qual o spot mais adequado para principiantes?\"",
    "detail": ""
  },
  {
    "type": "CTA-NO-DEST",
    "page": "surf-mobile",
    "msg": "CTA sem destino real: \"É necessário saber nadar para aprender surf?\"",
    "detail": ""
  },
  {
    "type": "CTA-NO-DEST",
    "page": "surf-mobile",
    "msg": "CTA sem destino real: \"Qual o equipamento básico necessário?\"",
    "detail": ""
  },
  {
    "type": "CTA-NO-DEST",
    "page": "surf-mobile",
    "msg": "CTA sem destino real: \"Posso surfar em Portugal durante todo o ano?\"",
    "detail": ""
  },
  {
    "type": "CTA-NO-DEST",
    "page": "surf-mobile",
    "msg": "CTA sem destino real: \"Quanto custa uma aula de surf em Portugal?\"",
    "detail": ""
  },
  {
    "type": "CTA-NO-DEST",
    "page": "surf-mobile",
    "msg": "CTA sem destino real: \"É perigoso surfar em Portugal para iniciantes?\"",
    "detail": ""
  },
  {
    "type": "CTA-NO-DEST",
    "page": "surf-mobile",
    "msg": "CTA sem destino real: \"MENU\"",
    "detail": ""
  },
  {
    "type": "JS-ERROR",
    "page": "_mobile",
    "msg": "Identifier 'SUPABASE_URL' has already been declared",
    "detail": ""
  },
  {
    "type": "JS-ERROR",
    "page": "_mobile",
    "msg": "Identifier 'SUPABASE_URL' has already been declared",
    "detail": ""
  },
  {
    "type": "CTA-NO-DEST",
    "page": "precos-mobile",
    "msg": "CTA sem destino real: \"Posso cancelar a qualquer momento?\"",
    "detail": ""
  },
  {
    "type": "CTA-NO-DEST",
    "page": "precos-mobile",
    "msg": "CTA sem destino real: \"O que acontece aos meus dados se cancelar?\"",
    "detail": ""
  },
  {
    "type": "CTA-NO-DEST",
    "page": "precos-mobile",
    "msg": "CTA sem destino real: \"Existe uma versão de teste gratuita do plano Pro?\"",
    "detail": ""
  },
  {
    "type": "CTA-NO-DEST",
    "page": "precos-mobile",
    "msg": "CTA sem destino real: \"O desconto anual aplica-se imediatamente?\"",
    "detail": ""
  },
  {
    "type": "CTA-NO-DEST",
    "page": "precos-mobile",
    "msg": "CTA sem destino real: \"O plano Partner serve para que tipo de negócios?\"",
    "detail": ""
  },
  {
    "type": "CTA-NO-DEST",
    "page": "precos-mobile",
    "msg": "CTA sem destino real: \"Como funciona a API de condições para parceiros?\"",
    "detail": ""
  },
  {
    "type": "CTA-NO-DEST",
    "page": "precos-mobile",
    "msg": "CTA sem destino real: \"Qual a diferença entre o plano Partner e a parceria completa\"",
    "detail": ""
  },
  {
    "type": "CTA-NO-DEST",
    "page": "parceiros-mobile",
    "msg": "CTA sem destino real: \"Submeter candidatura\"",
    "detail": ""
  },
  {
    "type": "JS-ERROR",
    "page": "_mobile",
    "msg": "Identifier 'SUPABASE_URL' has already been declared",
    "detail": ""
  },
  {
    "type": "CTA-NO-DEST",
    "page": "contact-mobile",
    "msg": "CTA sem destino real: \"Enviar Mensagem\"",
    "detail": ""
  },
  {
    "type": "CTA-NO-DEST",
    "page": "contact-mobile",
    "msg": "CTA sem destino real: \"Como me candidato a parceiro do portal?\"",
    "detail": ""
  },
  {
    "type": "CTA-NO-DEST",
    "page": "contact-mobile",
    "msg": "CTA sem destino real: \"Como funciona o serviço de planeamento de viagens?\"",
    "detail": ""
  },
  {
    "type": "CTA-NO-DEST",
    "page": "contact-mobile",
    "msg": "CTA sem destino real: \"Como posso sugerir uma praia que não está na plataforma?\"",
    "detail": ""
  },
  {
    "type": "CTA-NO-DEST",
    "page": "contact-mobile",
    "msg": "CTA sem destino real: \"Em quanto tempo recebo uma resposta?\"",
    "detail": ""
  },
  {
    "type": "CTA-NO-DEST",
    "page": "contact-mobile",
    "msg": "CTA sem destino real: \"Trabalham com imprensa e media?\"",
    "detail": ""
  }
]